matematik_klib/__init__.py
matematik_klib/__init__.pyi
matematik_klib-0.1.2.5.dist-info/licenses/LICENSE
matematik_klib-0.1.2.5.dist-info/METADATA
matematik_klib-0.1.2.5.dist-info/WHEEL
matematik_klib-0.1.2.5.dist-info/top_level.txt
matematik_klib-0.1.2.5.dist-info/RECORD
