Metadata-Version: 2.4
Name: matematik_klib
Version: 0.1.2.5
Summary: A small math library with polynomial solvers and power/root functions and Area
Author-email: Kian William Nørgaard Sørensen <kianersej12345@gmail.com>
License: MIT License
Project-URL: Repository, https://github.com/kian140908/matematik_klib
Project-URL: Documentation, https://github.com/kian140908/matematik_klib/wiki
Project-URL: Issues, https://github.com/kian140908/matematik_klib/issues
Keywords: math,polynomials,power,root,Area
Classifier: Programming Language :: Python :: 3
Classifier: Programming Language :: Python :: 3.9
Classifier: License :: OSI Approved :: MIT License
Classifier: Operating System :: OS Independent
Classifier: Intended Audience :: Developers
Classifier: Topic :: Software Development :: Libraries :: Python Modules
Requires-Python: >=3.9
License-File: LICENSE
Dynamic: license-file
